[
  {
    "id": 0,
    "nazev": "Bitcoin Node",
    "popis": "Návod na instalaci Bitcoin Node.",
    "md_navod": "/00_Bitcoin_Node.md",
    "odkaz": "#",
    "aktivni": false
  },
  {
    "id": 1,
    "nazev": "LAMP",
    "popis": "Návod na instalaci LAMP.",
    "md_navod": "/01_LAMP.md",
    "odkaz": "#",
    "aktivni": false
  },
  {
    "id": 2,
    "nazev": "WordPress",
    "popis": "Návod na instalaci WordPress.",
    "md_navod": "/02_WordPress.md",
    "odkaz": "#",
    "aktivni": false
  },
  {
    "id": 3,
    "nazev": "Nodejs",
    "popis": "Návod na instalaci Nodejs.",
    "md_navod": "/03_Nodejs.md",
    "odkaz": "#",
    "aktivni": false
  },
  {
    "id": 4,
    "nazev": "MySQL",
    "popis": "Návod na instalaci MySQL.",
    "md_navod": "/04_MySQL.md",
    "odkaz": "#",
    "aktivni": false
  },
  {
    "id": 5,
    "nazev": "PhpMyAdmin",
    "popis": "Návod na instalaci PhpMyAdmin.",
    "md_navod": "/05_PhpMyAdmin.md",
    "odkaz": "#",
    "aktivni": false
  },
  {
    "id": 6,
    "nazev": "PostgreSQL",
    "popis": "Návod na instalaci PostgreSQL.",
    "md_navod": "/06_PostgreSQL.md",
    "odkaz": "#",
    "aktivni": false
  },
  {
    "id": 7,
    "nazev": "InfluxDB",
    "popis": "Návod na instalaci InfluxDB.",
    "md_navod": "/07_InfluxDB.md",
    "odkaz": "#",
    "aktivni": false
  },
  {
    "id": 8,
    "nazev": "PiHole",
    "popis": "Návod na instalaci PiHole.",
    "md_navod": "/08_PiHole.md",
    "odkaz": "#",
    "aktivni": false
  },
  {
    "id": 9,
    "nazev": "Apache Guacamole",
    "popis": "Návod na instalaci Apache Guacamole.",
    "md_navod": "/09_Apache_Guacamole.md",
    "odkaz": "#",
    "aktivni": false
  },
  {
    "id": 10,
    "nazev": "Apache WebServer",
    "popis": "Návod na instalaci Apache WebServer.",
    "md_navod": "/10_Apache_WebServer.md",
    "odkaz": "#",
    "aktivni": false
  },
  {
    "id": 11,
    "nazev": "Nginx WebServer",
    "popis": "Návod na instalaci Nginx WebServer.",
    "md_navod": "/11_Nginx_WebServer.md",
    "odkaz": "#",
    "aktivni": false
  },
  {
    "id": 12,
    "nazev": "Nginx Proxy Manager",
    "popis": "Návod na instalaci Nginx Proxy Manager.",
    "md_navod": "/12_Nginx_Proxy_Manager.md",
    "odkaz": "#",
    "aktivni": false
  },
  {
    "id": 13,
    "nazev": "Zabbix",
    "popis": "Návod na instalaci Zabbix.",
    "md_navod": "/13_Zabbix.md",
    "odkaz": "#",
    "aktivni": false
  },
  {
    "id": 14,
    "nazev": "Grafana Prometheus",
    "popis": "Návod na instalaci Grafana Prometheus.",
    "md_navod": "/14_Grafana_Prometheus.md",
    "odkaz": "#",
    "aktivni": false
  },
  {
    "id": 15,
    "nazev": "Graylog",
    "popis": "Návod na instalaci Graylog.",
    "md_navod": "/15_Graylog.md",
    "odkaz": "#",
    "aktivni": false
  },
  {
    "id": 16,
    "nazev": "OpenVAS",
    "popis": "Návod na instalaci OpenVAS.",
    "md_navod": "/16_OpenVAS.md",
    "odkaz": "#",
    "aktivni": false
  },
  {
    "id": 17,
    "nazev": "Gitea",
    "popis": "Návod na instalaci Gitea.",
    "md_navod": "/17_Gitea.md",
    "odkaz": "#",
    "aktivni": false
  },
  {
    "id": 18,
    "nazev": "Jenkins",
    "popis": "Návod na instalaci Jenkins.",
    "md_navod": "/18_Jenkins.md",
    "odkaz": "#",
    "aktivni": false
  },
  {
    "id": 19,
    "nazev": "GhostCMS",
    "popis": "Návod na instalaci GhostCMS.",
    "md_navod": "/19_GhostCMS.md",
    "odkaz": "#",
    "aktivni": false
  },
  {
    "id": 20,
    "nazev": "MariaDB",
    "popis": "Návod na instalaci MariaDB.",
    "md_navod": "/20_MariaDB.md",
    "odkaz": "#",
    "aktivni": false
  },
  {
    "id": 21,
    "nazev": "Drupal",
    "popis": "Návod na instalaci Drupal.",
    "md_navod": "/21_Drupal.md",
    "odkaz": "#",
    "aktivni": false
  },
  {
    "id": 22,
    "nazev": "Joomla",
    "popis": "Návod na instalaci Joomla.",
    "md_navod": "/22_Joomla.md",
    "odkaz": "#",
    "aktivni": false
  },
  {
    "id": 23,
    "nazev": "Cassandra",
    "popis": "Návod na instalaci Cassandra.",
    "md_navod": "/23_Cassandra.md",
    "odkaz": "#",
    "aktivni": false
  },
  {
    "id": 24,
    "nazev": "Traefik",
    "popis": "Návod na instalaci Traefik.",
    "md_navod": "/24_Traefik.md",
    "odkaz": "#",
    "aktivni": false
  },
  {
    "id": 25,
    "nazev": "WireGuard",
    "popis": "Návod na instalaci WireGuard.",
    "md_navod": "/25_WireGuard.md",
    "odkaz": "#",
    "aktivni": false
  },
  {
    "id": 26,
    "nazev": "OpenVPN",
    "popis": "Návod na instalaci OpenVPN.",
    "md_navod": "/26_OpenVPN.md",
    "odkaz": "#",
    "aktivni": false
  },
  {
    "id": 27,
    "nazev": "PiVPN",
    "popis": "Návod na instalaci PiVPN.",
    "md_navod": "/27_PiVPN.md",
    "odkaz": "#",
    "aktivni": false
  },
  {
    "id": 28,
    "nazev": "Nextcloud",
    "popis": "Návod na instalaci Nextcloud.",
    "md_navod": "/28_Nextcloud.md",
    "odkaz": "#",
    "aktivni": false
  },
  {
    "id": 29,
    "nazev": "Seafile",
    "popis": "Návod na instalaci Seafile.",
    "md_navod": "/29_Seafile.md",
    "odkaz": "#",
    "aktivni": false
  },
  {
    "id": 31,
    "nazev": "AdGuard Home",
    "popis": "Návod na instalaci AdGuard Home.",
    "md_navod": "/31_AdGuard_Home.md",
    "odkaz": "#",
    "aktivni": false
  },
  {
    "id": 32,
    "nazev": "Netdata",
    "popis": "Návod na instalaci Netdata.",
    "md_navod": "/32_Netdata.md",
    "odkaz": "#",
    "aktivni": false
  },
  {
    "id": 33,
    "nazev": "Cockpit",
    "popis": "Návod na instalaci Cockpit.",
    "md_navod": "/33_Cockpit.md",
    "odkaz": "#",
    "aktivni": false
  },
  {
    "id": 34,
    "nazev": "Portainer",
    "popis": "Návod na instalaci Portainer.",
    "md_navod": "/34_Portainer.md",
    "odkaz": "#",
    "aktivni": false
  },
  {
    "id": 35,
    "nazev": "Syncthing",
    "popis": "Návod na instalaci Syncthing.",
    "md_navod": "/35_Syncthing.md",
    "odkaz": "#",
    "aktivni": false
  },
  {
    "id": 36,
    "nazev": "DNSCrypt-Proxy",
    "popis": "Návod na instalaci DNSCrypt-Proxy.",
    "md_navod": "/36_DNSCrypt-Proxy.md",
    "odkaz": "#",
    "aktivni": false
  },
  {
    "id": 37,
    "nazev": "Bind9",
    "popis": "Návod na instalaci Bind9.",
    "md_navod": "/37_Bind9.md",
    "odkaz": "#",
    "aktivni": false
  },
  {
    "id": 38,
    "nazev": "Postfix Dovecot",
    "popis": "Návod na instalaci Postfix Dovecot.",
    "md_navod": "/38_Postfix_Dovecot.md",
    "odkaz": "#",
    "aktivni": false
  },
  {
    "id": 39,
    "nazev": "Mailcow",
    "popis": "Návod na instalaci Mailcow.",
    "md_navod": "/39_Mailcow.md",
    "odkaz": "#",
    "aktivni": false
  },
  {
    "id": 40,
    "nazev": "ZeroTier",
    "popis": "Návod na instalaci ZeroTier.",
    "md_navod": "/40_ZeroTier.md",
    "odkaz": "#",
    "aktivni": false
  },
  {
    "id": 41,
    "nazev": "Vaultwarden",
    "popis": "Návod na instalaci Vaultwarden.",
    "md_navod": "/41_Vaultwarden.md",
    "odkaz": "#",
    "aktivni": false
  },
  {
    "id": 42,
    "nazev": "Glances",
    "popis": "Návod na instalaci Glances.",
    "md_navod": "/42_Glances.md",
    "odkaz": "#",
    "aktivni": false
  },
  {
    "id": 43,
    "nazev": "Homebox",
    "popis": "Návod na instalaci Homebox.",
    "md_navod": "/43_Homebox.md",
    "odkaz": "#",
    "aktivni": false
  },
  {
    "id": 44,
    "nazev": "Filebrowser",
    "popis": "Návod na instalaci Filebrowser.",
    "md_navod": "/44_Filebrowser.md",
    "odkaz": "#",
    "aktivni": false
  }
]